nonRegressionTestTools/__init__.py
nonRegressionTestTools/config.py
nonRegressionTestTools/constantes.py
nonRegressionTestTools/filters.py
nonRegressionTestTools/genericTestBase.py
nonRegressionTestTools/runners.py
nonRegressionTestTools/statutsManager.py
nonRegressionTestTools/testCase.py
nonRegressionTestTools-1.1.6.data/scripts/nrt-bilan
nonRegressionTestTools-1.1.6.data/scripts/nrt-create
nonRegressionTestTools-1.1.6.data/scripts/nrt-run
nonRegressionTestTools-1.1.6.data/scripts/nrt-savestate
nonRegressionTestTools-1.1.6.dist-info/LICENSE
nonRegressionTestTools-1.1.6.dist-info/METADATA
nonRegressionTestTools-1.1.6.dist-info/WHEEL
nonRegressionTestTools-1.1.6.dist-info/top_level.txt
nonRegressionTestTools-1.1.6.dist-info/RECORD
