Metadata-Version: 2.1
Name: nonRegressionTestTools
Version: 1.1.6
Summary: NonRegressionTestTools  
Author-email: teddy Chantrait <teddy.chantrait@gmail.com>
Maintainer-email: teddy Chantrait <teddy.chantrait@gmail.com>
License: GNU LESSER GENERAL PUBLIC LICENSE
Project-URL: Homepage, https://gitlab.com/Te_ch/non-regression-test-tools
Project-URL: Documentation, https://te_ch.gitlab.io/non-regression-test-tools
Project-URL: Repository, https://gitlab.com/Te_ch/non-regression-test-tools.git
Classifier: Development Status :: 4 - Beta
Classifier: License :: OSI Approved :: GNU General Public License v2 (GPLv2)
Classifier: Programming Language :: Python :: 3 :: Only
Classifier: Programming Language :: Python :: 3.10
Classifier: Programming Language :: Python :: 3.11
Classifier: Programming Language :: Python :: 3.12
Requires-Python: >=3.10
License-File: LICENSE
Requires-Dist: numpy >=1.26
